{
  "version": "1.1",
  "last_updated": "2025-08-12",
  "total_listings": 40,
  "listings": [
    {
      "id": 1,
      "title": "Nyali Luxury Apartments",
      "slug": "nyali-luxury-apartments-1",
      "url": "listing_detail.html?id=1",
      "description": "Modern 3-bedroom units with sea view and fiber Wi-Fi.",
      "category": "Accommodation",
      "subcategory": "Apartments",
      "region": "Mombasa",
      "rating": 3.5,
      "reviews": 50,
      "date_posted": "2025-07-01",
      "created_at": "2025-07-01T00:00:00Z",
      "owner": "lesly",
      "image": "images/listings/apartment.webp",
      "package": "Gold",
      "package_priority": 100,
      "badge_color": "gold",
      "featured": true,
      "coords": { "lat": -4.0435, "lon": 39.6682 },
      "tags": ["accommodation", "apartments", "mombasa", "gold"],
      "views": 750
    },
    {
      "id": 2,
      "title": "Mama Amina’s Kitchen",
      "slug": "mama-aminas-kitchen-2",
      "url": "listing_detail.html?id=2",
      "description": "Authentic Swahili dishes and homemade tamarind juice.",
      "category": "Food & Dining",
      "subcategory": "Local Kitchens",
      "region": "Kilifi",
      "rating": 4.0,
      "reviews": 53,
      "date_posted": "2025-07-02",
      "created_at": "2025-07-02T00:00:00Z",
      "owner": "guest",
      "image": "images/listings/swahili.webp",
      "package": "Silver",
      "package_priority": 30,
      "badge_color": "silver",
      "featured": false,
      "coords": { "lat": -3.6333, "lon": 39.8500 },
      "tags": ["food", "local-kitchens", "kilifi", "basic"],
      "views": 795
    },
    {
      "id": 3,
      "title": "Lamu Sunset Cruise",
      "slug": "lamu-sunset-cruise-3",
      "url": "listing_detail.html?id=3",
      "description": "Evening dhow rides with grilled seafood and music.",
      "category": "Tourism & Attractions",
      "subcategory": "Boat Tours",
      "region": "Lamu",
      "rating": 5.0,
      "reviews": 56,
      "date_posted": "2025-07-03",
      "created_at": "2025-07-03T00:00:00Z",
      "owner": "lesly",
      "image": "images/listings/dhow.webp",
      "package": "Gold",
      "package_priority": 100,
      "badge_color": "gold",
      "featured": true,
      "coords": { "lat": -2.2711, "lon": 40.9028 },
      "tags": ["tourism", "boat-tours", "lamu", "gold"],
      "views": 840
    },
    {
      "id": 4,
      "title": "Kwale Wellness Center",
      "slug": "kwale-wellness-center-4",
      "url": "listing_detail.html?id=4",
      "description": "Outpatient clinic with labs and counseling support.",
      "category": "Health & Wellness",
      "subcategory": "Clinics",
      "region": "Kwale",
      "rating": 3.0,
      "reviews": 59,
      "date_posted": "2025-07-04",
      "created_at": "2025-07-04T00:00:00Z",
      "owner": "guest",
      "image": "images/listings/clinic.webp",
      "package": "Bronze",
      "package_priority": 50,
      "badge_color": "bronze",
      "featured": false,
      "coords": { "lat": -4.2860, "lon": 39.4510 },
      "tags": ["health", "clinics", "kwale", "bronze"],
      "views": 885
    },
    {
      "id": 5,
      "title": "Wundanyi Cyber Café",
      "slug": "wundanyi-cyber-cafe-5",
      "url": "listing_detail.html?id=5",
      "description": "Printing, browsing and e-citizen access available.",
      "category": "Tech & Digital Services",
      "subcategory": "Cyber Cafes",
      "region": "Taita Taveta",
      "rating": 4.5,
      "reviews": 62,
      "date_posted": "2025-07-05",
      "created_at": "2025-07-05T00:00:00Z",
      "owner": "lesly",
      "image": "images/listings/cyber.webp",
      "package": "Slver",
      "package_priority": 30,
      "badge_color": "silver",
      "featured": false,
      "coords": { "lat": -3.3968, "lon": 38.5544 },
      "tags": ["tech", "cyber-cafe", "taita-taveta", "basic"],
      "views": 930
    },
    {
      "id": 6,
      "title": "Hola ICT Academy",
      "slug": "hola-ict-academy-6",
      "url": "listing_detail.html?id=6",
      "description": "Courses in digital skills and coding for beginners.",
      "category": "Education & Learning",
      "subcategory": "ICT Training",
      "region": "Tana River",
      "rating": 5.0,
      "reviews": 65,
      "date_posted": "2025-07-06",
      "created_at": "2025-07-06T00:00:00Z",
      "owner": "guest",
      "image": "images/listings/computer.webp",
      "package": "Bronze",
      "package_priority": 50,
      "badge_color": "bronze",
      "featured": false,
      "coords": { "lat": -1.4500, "lon": 40.0500 },
      "tags": ["education", "ict", "tana-river", "bronze"],
      "views": 975
    },
    {
      "id": 7,
      "title": "Mvita Hair Lounge",
      "slug": "mvita-hair-lounge-7",
      "url": "listing_detail.html?id=7",
      "description": "Professional grooming, nails and hair styling.",
      "category": "Beauty & Grooming",
      "subcategory": "Salons",
      "region": "Mombasa",
      "rating": 3.5,
      "reviews": 68,
      "date_posted": "2025-07-07",
      "created_at": "2025-07-07T00:00:00Z",
      "owner": "lesly",
      "image": "images/listings/saloon.webp",
      "package": "Silver",
      "package_priority": 30,
      "badge_color": "silver",
      "featured": false,
      "coords": { "lat": -4.0435, "lon": 39.6682 },
      "tags": ["beauty", "salons", "mombasa", "basic"],
      "views": 1020
    },
    {
      "id": 8,
      "title": "Kilifi SACCO Services",
      "slug": "kilifi-sacco-services-8",
      "url": "listing_detail.html?id=8",
      "description": "Loans, savings & investment support for locals.",
      "category": "Financial Services",
      "subcategory": "SACCOs",
      "region": "Kilifi",
      "rating": 4.0,
      "reviews": 71,
      "date_posted": "2025-07-08",
      "created_at": "2025-07-08T00:00:00Z",
      "owner": "guest",
      "image": "images/listings/sacco.webp",
      "package": "Gold",
      "package_priority": 100,
      "badge_color": "gold",
      "featured": true,
      "coords": { "lat": -3.6333, "lon": 39.8500 },
      "tags": ["finance", "sacco", "kilifi", "gold"],
      "views": 1065
    },
    {
      "id": 9,
      "title": "Kwale Builders Hub",
      "slug": "kwale-builders-hub-9",
      "url": "listing_detail.html?id=9",
      "description": "Tools, fundi referrals & site support available.",
      "category": "Construction & Real Estate",
      "subcategory": "Contractors",
      "region": "Kwale",
      "rating": 5.0,
      "reviews": 74,
      "date_posted": "2025-07-09",
      "created_at": "2025-07-09T00:00:00Z",
      "owner": "lesly",
      "image": "images/listings/builders.webp",
      "package": "Silver",
      "package_priority": 30,
      "badge_color": "silver",
      "featured": false,
      "coords": { "lat": -4.2860, "lon": 39.4510 },
      "tags": ["construction", "contractors", "kwale", "basic"],
      "views": 1110
    },
    {
      "id": 10,
      "title": "Taita Agro Market",
      "slug": "taita-agro-market-10",
      "url": "listing_detail.html?id=10",
      "description": "Livestock, seeds & agro tools for small-scale farmers.",
      "category": "Farmers & Agribusiness",
      "subcategory": "Livestock",
      "region": "Taita Taveta",
      "rating": 3.0,
      "reviews": 77,
      "date_posted": "2025-07-10",
      "created_at": "2025-07-10T00:00:00Z",
      "owner": "guest",
      "image": "images/listings/market.webp",
      "package": "Bronze",
      "package_priority": 50,
      "badge_color": "bronze",
      "featured": false,
      "coords": { "lat": -3.3968, "lon": 38.5544 },
      "tags": ["agriculture", "livestock", "taita-taveta", "bronze"],
      "views": 1155
    },
    {
      "id": 11,
      "title": "Lamu Pet Care",
      "slug": "lamu-pet-care-11",
      "url": "listing_detail.html?id=11",
      "description": "Vet visits, grooming and pet adoption support.",
      "category": "Pet & Animal Services",
      "subcategory": "Vets",
      "region": "Lamu",
      "rating": 4.5,
      "reviews": 80,
      "date_posted": "2025-07-11",
      "created_at": "2025-07-11T00:00:00Z",
      "owner": "lesly",
      "image": "images/listings/pet.webp",
      "package": "Silver",
      "package_priority": 30,
      "badge_color": "slver",
      "featured": false,
      "coords": { "lat": -2.2711, "lon": 40.9028 },
      "tags": ["pets", "vets", "lamu", "basic"],
      "views": 1200
    },
    {
      "id": 12,
      "title": "Nyali Express Delivery",
      "slug": "nyali-express-delivery-12",
      "url": "listing_detail.html?id=12",
      "description": "Boda riders for same-day delivery across Mombasa.",
      "category": "Delivery & Errands",
      "subcategory": "Boda Delivery",
      "region": "Mombasa",
      "rating": 5.0,
      "reviews": 83,
      "date_posted": "2025-07-12",
      "created_at": "2025-07-12T00:00:00Z",
      "owner": "guest",
      "image": "images/listings/delivery1.webp",
      "package": "Bronze",
      "package_priority": 50,
      "badge_color": "bronze",
      "featured": false,
      "coords": { "lat": -4.0435, "lon": 39.6682 },
      "tags": ["delivery", "boda", "mombasa", "bronze"],
      "views": 1245
    },
    {
      "id": 13,
      "title": "Shela Yoga Retreat",
      "slug": "shela-yoga-retreat-13",
      "url": "listing_detail.html?id=13",
      "description": "Morning yoga and mindfulness with ocean views.",
      "category": "Health & Wellness",
      "subcategory": "Retreats",
      "region": "Lamu",
      "rating": 3.5,
      "reviews": 86,
      "date_posted": "2025-07-13",
      "created_at": "2025-07-13T00:00:00Z",
      "owner": "lesly",
      "image": "images/listings/yoga.webp",
      "package": "Bronze",
      "package_priority": 50,
      "badge_color": "bronze",
      "featured": false,
      "coords": { "lat": -2.2711, "lon": 40.9028 },
      "tags": ["wellness", "yoga", "lamu", "bronze"],
      "views": 1290
    },
    {
      "id": 14,
      "title": "Mombasa Coding Hub",
      "slug": "mombasa-coding-hub-14",
      "url": "listing_detail.html?id=14",
      "description": "Evening bootcamps and hackathons for youth.",
      "category": "Education & Learning",
      "subcategory": "Coding Schools",
      "region": "Mombasa",
      "rating": 4.0,
      "reviews": 89,
      "date_posted": "2025-07-14",
      "created_at": "2025-07-14T00:00:00Z",
      "owner": "guest",
      "image": "images/listings/code.webp",
      "package": "Gold",
      "package_priority": 100,
      "badge_color": "gold",
      "featured": true,
      "coords": { "lat": -4.0435, "lon": 39.6682 },
      "tags": ["education", "coding", "mombasa", "gold"],
      "views": 1335
    },
    {
      "id": 15,
      "title": "Kilifi Fishing Charters",
      "slug": "kilifi-fishing-charters-15",
      "url": "listing_detail.html?id=15",
      "description": "Deep sea fishing for groups and tourists.",
      "category": "Tourism & Attractions",
      "subcategory": "Fishing",
      "region": "Kilifi",
      "rating": 5.0,
      "reviews": 92,
      "date_posted": "2025-07-15",
      "created_at": "2025-07-15T00:00:00Z",
      "owner": "lesly",
      "image": "images/listings/fishing.webp",
      "package": "Silver",
      "package_priority": 30,
      "badge_color": "silver",
      "featured": false,
      "coords": { "lat": -3.6333, "lon": 39.8500 },
      "tags": ["tourism", "fishing", "kilifi", "basic"],
      "views": 1380
    },
    {
      "id": 16,
      "title": "Voi Hardware Mall",
      "slug": "voi-hardware-mall-16",
      "url": "listing_detail.html?id=16",
      "description": "Construction tools and building materials.",
      "category": "Construction & Real Estate",
      "subcategory": "Hardware Stores",
      "region": "Taita Taveta",
      "rating": 3.0,
      "reviews": 95,
      "date_posted": "2025-07-16",
      "created_at": "2025-07-16T00:00:00Z",
      "owner": "guest",
      "image": "images/listings/hardware.webp",
      "package": "Gold",
      "package_priority": 100,
      "badge_color": "gold",
      "featured": true,
      "coords": { "lat": -3.3968, "lon": 38.5544 },
      "tags": ["construction", "hardware", "taita-taveta", "gold"],
      "views": 1425
    },
    {
      "id": 17,
      "title": "Kwale Print & Stationers",
      "slug": "kwale-print-stationers-17",
      "url": "listing_detail.html?id=17",
      "description": "Business cards, flyers, and office supplies.",
      "category": "Tech & Digital Services",
      "subcategory": "Printing",
      "region": "Kwale",
      "rating": 4.5,
      "reviews": 98,
      "date_posted": "2025-07-17",
      "created_at": "2025-07-17T00:00:00Z",
      "owner": "lesly",
      "image": "images/listings/printing.webp",
      "package": "Silver",
      "package_priority": 30,
      "badge_color": "silver",
      "featured": false,
      "coords": { "lat": -4.2860, "lon": 39.4510 },
      "tags": ["printing", "office", "kwale", "basic"],
      "views": 1470
    },
    {
      "id": 18,
      "title": "Tana River Car Wash",
      "slug": "tana-river-car-wash-18",
      "url": "listing_detail.html?id=18",
      "description": "Eco-friendly car wash with interior detailing.",
      "category": "Automotive",
      "subcategory": "Car Wash",
      "region": "Tana River",
      "rating": 5.0,
      "reviews": 101,
      "date_posted": "2025-07-18",
      "created_at": "2025-07-18T00:00:00Z",
      "owner": "guest",
      "image": "images/listings/carwash.webp",
      "package": "Bronze",
      "package_priority": 50,
      "badge_color": "bronze",
      "featured": false,
      "coords": { "lat": -1.4500, "lon": 40.0500 },
      "tags": ["automotive", "carwash", "tana-river", "bronze"],
      "views": 1515
    },
    {
      "id": 19,
      "title": "Lamu Handcrafted Decor",
      "slug": "lamu-handcrafted-decor-19",
      "url": "listing_detail.html?id=19",
      "description": "Locally made art pieces and coastal décor.",
      "category": "Art & Culture",
      "subcategory": "Craft Shops",
      "region": "Lamu",
      "rating": 3.5,
      "reviews": 104,
      "date_posted": "2025-07-19",
      "created_at": "2025-07-19T00:00:00Z",
      "owner": "lesly",
      "image": "images/listings/decor.webp",
      "package": "Silver",
      "package_priority": 30,
      "badge_color": "silver",
      "featured": false,
      "coords": { "lat": -2.2711, "lon": 40.9028 },
      "tags": ["art", "crafts", "lamu", "basic"],
      "views": 1560
    },
    {
      "id": 20,
      "title": "Mombasa Fitness Studio",
      "slug": "mombasa-fitness-studio-20",
      "url": "listing_detail.html?id=20",
      "description": "Group workouts, Zumba, and personal training.",
      "category": "Health & Wellness",
      "subcategory": "Gyms",
      "region": "Mombasa",
      "rating": 4.0,
      "reviews": 107,
      "date_posted": "2025-07-20",
      "created_at": "2025-07-20T00:00:00Z",
      "owner": "guest",
      "image": "images/listings/fitness.webp",
      "package": "Gold",
      "package_priority": 100,
      "badge_color": "gold",
      "featured": true,
      "coords": { "lat": -4.0435, "lon": 39.6682 },
      "tags": ["fitness", "gym", "mombasa", "gold"],
      "views": 1605
    },
    {
      "id": 21,
      "title": "Nyali Luxury Apartments",
      "slug": "nyali-luxury-apartments-21",
      "url": "listing_detail.html?id=21",
      "description": "Modern 3-bedroom units with sea view and fiber Wi-Fi.",
      "category": "Accommodation",
      "subcategory": "Apartments",
      "region": "Mombasa",
      "rating": 5.0,
      "reviews": 110,
      "date_posted": "2025-07-21",
      "created_at": "2025-07-21T00:00:00Z",
      "owner": "lesly",
      "image": "images/listings/apartment.webp",
      "package": "Gold",
      "package_priority": 100,
      "badge_color": "gold",
      "featured": true,
      "coords": { "lat": -4.0435, "lon": 39.6682 },
      "tags": ["accommodation", "apartments", "mombasa", "gold"],
      "views": 1650
    },
    {
      "id": 22,
      "title": "Mama Amina’s Kitchen",
      "slug": "mama-aminas-kitchen-22",
      "url": "listing_detail.html?id=22",
      "description": "Authentic Swahili dishes and homemade tamarind juice.",
      "category": "Food & Dining",
      "subcategory": "Local Kitchens",
      "region": "Kilifi",
      "rating": 3.0,
      "reviews": 113,
      "date_posted": "2025-07-22",
      "created_at": "2025-07-22T00:00:00Z",
      "owner": "guest",
      "image": "images/listings/swahili.webp",
      "package": "Silver",
      "package_priority": 30,
      "badge_color": "silver",
      "featured": false,
      "coords": { "lat": -3.6333, "lon": 39.8500 },
      "tags": ["food", "local-kitchens", "kilifi", "basic"],
      "views": 1695
    },
    {
      "id": 23,
      "title": "Lamu Sunset Cruise",
      "slug": "lamu-sunset-cruise-23",
      "url": "listing_detail.html?id=23",
      "description": "Evening dhow rides with grilled seafood and music.",
      "category": "Tourism & Attractions",
      "subcategory": "Boat Tours",
      "region": "Lamu",
      "rating": 4.5,
      "reviews": 116,
      "date_posted": "2025-07-23",
      "created_at": "2025-07-23T00:00:00Z",
      "owner": "lesly",
      "image": "images/listings/dhow.webp",
      "package": "Gold",
      "package_priority": 100,
      "badge_color": "gold",
      "featured": true,
      "coords": { "lat": -2.2711, "lon": 40.9028 },
      "tags": ["tourism", "boat-tours", "lamu", "gold"],
      "views": 1740
    },
    {
      "id": 24,
      "title": "Kwale Wellness Center",
      "slug": "kwale-wellness-center-24",
      "url": "listing_detail.html?id=24",
      "description": "Outpatient clinic with labs and counseling support.",
      "category": "Health & Wellness",
      "subcategory": "Clinics",
      "region": "Kwale",
      "rating": 5.0,
      "reviews": 119,
      "date_posted": "2025-07-24",
      "created_at": "2025-07-24T00:00:00Z",
      "owner": "guest",
      "image": "images/listings/clinic.webp",
      "package": "Bronze",
      "package_priority": 50,
      "badge_color": "bronze",
      "featured": false,
      "coords": { "lat": -4.2860, "lon": 39.4510 },
      "tags": ["health", "clinics", "kwale", "bronze"],
      "views": 1785
    },
    {
      "id": 25,
      "title": "Wundanyi Cyber Café",
      "slug": "wundanyi-cyber-cafe-25",
      "url": "listing_detail.html?id=25",
      "description": "Printing, browsing and e-citizen access available.",
      "category": "Tech & Digital Services",
      "subcategory": "Cyber Cafes",
      "region": "Taita Taveta",
      "rating": 3.5,
      "reviews": 122,
      "date_posted": "2025-07-25",
      "created_at": "2025-07-25T00:00:00Z",
      "owner": "lesly",
      "image": "images/listings/cyber.webp",
      "package": "Silver",
      "package_priority": 30,
      "badge_color": "silver",
      "featured": false,
      "coords": { "lat": -3.3968, "lon": 38.5544 },
      "tags": ["tech", "cyber-cafe", "taita-taveta", "basic"],
      "views": 1830
    },
    {
      "id": 26,
      "title": "Hola ICT Academy",
      "slug": "hola-ict-academy-26",
      "url": "listing_detail.html?id=26",
      "description": "Courses in digital skills and coding for beginners.",
      "category": "Education & Learning",
      "subcategory": "ICT Training",
      "region": "Tana River",
      "rating": 4.0,
      "reviews": 125,
      "date_posted": "2025-07-26",
      "created_at": "2025-07-26T00:00:00Z",
      "owner": "guest",
      "image": "images/listings/computer.webp",
      "package": "Bronze",
      "package_priority": 50,
      "badge_color": "bronze",
      "featured": false,
      "coords": { "lat": -1.4500, "lon": 40.0500 },
      "tags": ["education", "ict", "tana-river", "bronze"],
      "views": 1875
    },
    {
      "id": 27,
      "title": "Mvita Hair Lounge",
      "slug": "mvita-hair-lounge-27",
      "url": "listing_detail.html?id=27",
      "description": "Professional grooming, nails and hair styling.",
      "category": "Beauty & Grooming",
      "subcategory": "Salons",
      "region": "Mombasa",
      "rating": 5.0,
      "reviews": 128,
      "date_posted": "2025-07-27",
      "created_at": "2025-07-27T00:00:00Z",
      "owner": "lesly",
      "image": "images/listings/saloon.webp",
      "package": "Silver",
      "package_priority": 30,
      "badge_color": "silver",
      "featured": false,
      "coords": { "lat": -4.0435, "lon": 39.6682 },
      "tags": ["beauty", "salons", "mombasa", "basic"],
      "views": 1920
    },
    {
      "id": 28,
      "title": "Kilifi SACCO Services",
      "slug": "kilifi-sacco-services-28",
      "url": "listing_detail.html?id=28",
      "description": "Loans, savings & investment support for locals.",
      "category": "Financial Services",
      "subcategory": "SACCOs",
      "region": "Kilifi",
      "rating": 3.0,
      "reviews": 131,
      "date_posted": "2025-07-28",
      "created_at": "2025-07-28T00:00:00Z",
      "owner": "guest",
      "image": "images/listings/sacco.webp",
      "package": "Gold",
      "package_priority": 100,
      "badge_color": "gold",
      "featured": true,
      "coords": { "lat": -3.6333, "lon": 39.8500 },
      "tags": ["finance", "sacco", "kilifi", "gold"],
      "views": 1965
    },
    {
      "id": 29,
      "title": "Kwale Builders Hub",
      "slug": "kwale-builders-hub-29",
      "url": "listing_detail.html?id=29",
      "description": "Tools, fundi referrals & site support available.",
      "category": "Construction & Real Estate",
      "subcategory": "Contractors",
      "region": "Kwale",
      "rating": 4.5,
      "reviews": 134,
      "date_posted": "2025-07-29",
      "created_at": "2025-07-29T00:00:00Z",
      "owner": "lesly",
      "image": "images/listings/builders.webp",
      "package": "Silver",
      "package_priority": 30,
      "badge_color": "silver",
      "featured": false,
      "coords": { "lat": -4.2860, "lon": 39.4510 },
      "tags": ["construction", "contractors", "kwale", "basic"],
      "views": 2010
    },
    {
      "id": 30,
      "title": "Taita Agro Market",
      "slug": "taita-agro-market-30",
      "url": "listing_detail.html?id=30",
      "description": "Livestock, seeds & agro tools for small-scale farmers.",
      "category": "Farmers & Agribusiness",
      "subcategory": "Livestock",
      "region": "Taita Taveta",
      "rating": 5.0,
      "reviews": 137,
      "date_posted": "2025-07-30",
      "created_at": "2025-07-30T00:00:00Z",
      "owner": "guest",
      "image": "images/listings/market.webp",
      "package": "Bronze",
      "package_priority": 50,
      "badge_color": "bronze",
      "featured": false,
      "coords": { "lat": -3.3968, "lon": 38.5544 },
      "tags": ["agriculture", "livestock", "taita-taveta", "bronze"],
      "views": 2055
    },
    {
      "id": 31,
      "title": "Malindi Sunset Photography",
      "slug": "malindi-sunset-photography-31",
      "url": "listing_detail.html?id=31",
      "description": "Professional beachside photo sessions with drone shots.",
      "category": "Art & Culture",
      "subcategory": "Photography",
      "region": "Kilifi",
      "rating": 4.8,
      "reviews": 172,
      "date_posted": "2025-08-10",
      "created_at": "2025-08-10T00:00:00Z",
      "owner": "lesly",
      "image": "images/listings/photography.webp",
      "package": "Gold",
      "package_priority": 100,
      "badge_color": "gold",
      "featured": true,
      "coords": { "lat": -3.2190, "lon": 40.1167 },
      "tags": ["photography", "malindi", "kilifi", "gold"],
      "views": 2580
    },
    {
      "id": 32,
      "title": "Likoni Fresh Fish Market",
      "slug": "likoni-fresh-fish-market-32",
      "url": "listing_detail.html?id=32",
      "description": "Daily fresh catches direct from local fishermen.",
      "category": "Food & Dining",
      "subcategory": "Seafood",
      "region": "Mombasa",
      "rating": 4.3,
      "reviews": 98,
      "date_posted": "2025-08-11",
      "created_at": "2025-08-11T00:00:00Z",
      "owner": "guest",
      "image": "images/listings/fishmarket.webp",
      "package": "Silver",
      "package_priority": 70,
      "badge_color": "silver",
      "featured": true,
      "coords": { "lat": -4.0427, "lon": 39.6836 },
      "tags": ["food", "seafood", "mombasa", "silver"],
      "views": 1470
    },
    {
      "id": 33,
      "title": "Watamu Kite Surfing School",
      "slug": "watamu-kite-surfing-school-33",
      "url": "listing_detail.html?id=33",
      "description": "Lessons and equipment rentals for all skill levels.",
      "category": "Tourism & Attractions",
      "subcategory": "Water Sports",
      "region": "Kilifi",
      "rating": 5.0,
      "reviews": 65,
      "date_posted": "2025-08-12",
      "created_at": "2025-08-12T00:00:00Z",
      "owner": "lesly",
      "image": "images/listings/kitesurf.webp",
      "package": "Gold",
      "package_priority": 100,
      "badge_color": "gold",
      "featured": true,
      "coords": { "lat": -3.3556, "lon": 40.0111 },
      "tags": ["watersports", "kitesurf", "watamu", "gold"],
      "views": 975
    },
    {
      "id": 34,
      "title": "Shanzu Furniture Works",
      "slug": "shanzu-furniture-works-34",
      "url": "listing_detail.html?id=34",
      "description": "Handcrafted Swahili-style furniture made from hardwood.",
      "category": "Construction & Real Estate",
      "subcategory": "Furniture",
      "region": "Mombasa",
      "rating": 4.6,
      "reviews": 150,
      "date_posted": "2025-08-13",
      "created_at": "2025-08-13T00:00:00Z",
      "owner": "guest",
      "image": "images/listings/furniture.webp",
      "package": "Bronze",
      "package_priority": 50,
      "badge_color": "bronze",
      "featured": false,
      "coords": { "lat": -3.9716, "lon": 39.7355 },
      "tags": ["furniture", "crafts", "mombasa", "bronze"],
      "views": 2250
    },
    {
      "id": 35,
      "title": "Taita Hills Hiking Tours",
      "slug": "taita-hills-hiking-tours-35",
      "url": "listing_detail.html?id=35",
      "description": "Guided treks with camping options and wildlife spotting.",
      "category": "Tourism & Attractions",
      "subcategory": "Hiking",
      "region": "Taita Taveta",
      "rating": 4.9,
      "reviews": 77,
      "date_posted": "2025-08-14",
      "created_at": "2025-08-14T00:00:00Z",
      "owner": "lesly",
      "image": "images/listings/hiking.webp",
      "package": "Gold",
      "package_priority": 100,
      "badge_color": "gold",
      "featured": true,
      "coords": { "lat": -3.3500, "lon": 38.6000 },
      "tags": ["hiking", "taita-hills", "taita-taveta", "gold"],
      "views": 1155
    },
    {
      "id": 36,
      "title": "Kwale Organic Farm",
      "slug": "kwale-organic-farm-36",
      "url": "listing_detail.html?id=36",
      "description": "Farm visits with fresh produce and agri-training sessions.",
      "category": "Farmers & Agribusiness",
      "subcategory": "Organic Farming",
      "region": "Kwale",
      "rating": 4.5,
      "reviews": 83,
      "date_posted": "2025-08-15",
      "created_at": "2025-08-15T00:00:00Z",
      "owner": "guest",
      "image": "images/listings/organicfarm.webp",
      "package": "Silver",
      "package_priority": 70,
      "badge_color": "silver",
      "featured": false,
      "coords": { "lat": -4.2000, "lon": 39.4500 },
      "tags": ["organic", "farm", "kwale", "silver"],
      "views": 1245
    },
    {
      "id": 37,
      "title": "Lamu Artisans Collective",
      "slug": "lamu-artisans-collective-37",
      "url": "listing_detail.html?id=37",
      "description": "Local artists selling handmade crafts, jewelry, and fabrics.",
      "category": "Art & Culture",
      "subcategory": "Craft Markets",
      "region": "Lamu",
      "rating": 4.7,
      "reviews": 102,
      "date_posted": "2025-08-16",
      "created_at": "2025-08-16T00:00:00Z",
      "owner": "lesly",
      "image": "images/listings/craftmarket.webp",
      "package": "Silver",
      "package_priority": 30,
      "badge_color": "silver",
      "featured": false,
      "coords": { "lat": -2.2711, "lon": 40.9028 },
      "tags": ["art", "crafts", "lamu", "basic"],
      "views": 1530
    },
    {
      "id": 38,
      "title": "Garsen Coffee Roasters",
      "slug": "garsen-coffee-roasters-38",
      "url": "listing_detail.html?id=38",
      "description": "Specialty Kenyan coffee roasted fresh every week.",
      "category": "Food & Dining",
      "subcategory": "Cafes",
      "region": "Tana River",
      "rating": 4.4,
      "reviews": 54,
      "date_posted": "2025-08-17",
      "created_at": "2025-08-17T00:00:00Z",
      "owner": "guest",
      "image": "images/listings/coffee.webp",
      "package": "Bronze",
      "package_priority": 50,
      "badge_color": "bronze",
      "featured": false,
      "coords": { "lat": -1.2600, "lon": 40.1000 },
      "tags": ["coffee", "cafes", "tana-river", "bronze"],
      "views": 810
    },
    {
      "id": 39,
      "title": "Ukunda Diving Adventures",
      "slug": "ukunda-diving-adventures-39",
      "url": "listing_detail.html?id=39",
      "description": "PADI certified diving courses and reef explorations.",
      "category": "Tourism & Attractions",
      "subcategory": "Diving",
      "region": "Kwale",
      "rating": 5.0,
      "reviews": 89,
      "date_posted": "2025-08-18",
      "created_at": "2025-08-18T00:00:00Z",
      "owner": "lesly",
      "image": "images/listings/diving.webp",
      "package": "Gold",
      "package_priority": 100,
      "badge_color": "gold",
      "featured": true,
      "coords": { "lat": -4.2969, "lon": 39.3456 },
      "tags": ["diving", "ukunda", "kwale", "gold"],
      "views": 1335
    },
    {
      "id": 40,
      "title": "Mtwapa Fitness & Wellness",
      "slug": "mtwapa-fitness-wellness-40",
      "url": "listing_detail.html?id=40",
      "description": "Full gym with spa, sauna, and yoga classes.",
      "category": "Health & Wellness",
      "subcategory": "Gyms",
      "region": "Kilifi",
      "rating": 4.6,
      "reviews": 131,
      "date_posted": "2025-08-19",
      "created_at": "2025-08-19T00:00:00Z",
      "owner": "guest",
      "image": "images/listings/gym.webp",
      "package": "Silver",
      "package_priority": 70,
      "badge_color": "silver",
      "featured": true,
      "coords": { "lat": -3.6350, "lon": 39.8550 },
      "tags": ["fitness", "gym", "kilifi", "silver"],
      "views": 1965
    }
  ]
}
